django_auth_ldap3/__init__.py
django_auth_ldap3/backends.py
django_auth_ldap3/conf.py
django_auth_ldap3-0.9.6.dist-info/DESCRIPTION.rst
django_auth_ldap3-0.9.6.dist-info/METADATA
django_auth_ldap3-0.9.6.dist-info/RECORD
django_auth_ldap3-0.9.6.dist-info/WHEEL
django_auth_ldap3-0.9.6.dist-info/metadata.json
django_auth_ldap3-0.9.6.dist-info/top_level.txt
